genomad/__init__.py
genomad/_paths.py
genomad/aragorn.py
genomad/cli.py
genomad/database.py
genomad/mmseqs2.py
genomad/prodigal.py
genomad/sequence.py
genomad/taxonomy.py
genomad/utils.py
genomad/data/decision_forest.ubj
genomad/data/nn_classifier.h5
genomad/data/provirus_tagger.crfsuite
genomad/data/rbs_categories.tsv
genomad/data/score_calibration_weights.npz
genomad/data/score_calibration_weights.py
genomad/modules/__init__.py
genomad/modules/aggregated_classification.py
genomad/modules/annotate.py
genomad/modules/download.py
genomad/modules/find_proviruses.py
genomad/modules/marker_classification.py
genomad/modules/nn_classification.py
genomad/modules/score_calibration.py
genomad/modules/summary.py
genomad/neural_network/__init__.py
genomad/neural_network/igloo.py
genomad/neural_network/model.py
genomad-1.11.2.data/data/decision_forest.ubj
genomad-1.11.2.data/data/nn_classifier.h5
genomad-1.11.2.data/data/provirus_tagger.crfsuite
genomad-1.11.2.data/data/rbs_categories.tsv
genomad-1.11.2.data/data/score_calibration_weights.npz
genomad-1.11.2.data/data/score_calibration_weights.py
genomad-1.11.2.dist-info/entry_points.txt
genomad-1.11.2.dist-info/licenses/LICENSE
genomad-1.11.2.dist-info/WHEEL
genomad-1.11.2.dist-info/METADATA
genomad-1.11.2.dist-info/RECORD
