Metadata-Version: 2.4
Name: genomad
Version: 1.11.2
Summary: geNomad: Identification of mobile genetic elements
Author-email: Antonio Camargo <antoniop.camargo@lbl.gov>
Requires-Python: >=3.9
License-File: LICENSE
Requires-Dist: keras >=3
Requires-Dist: numba >=0.57
Requires-Dist: numpy >=1.21
Requires-Dist: pyrodigal-gv >=0.3.1
Requires-Dist: python-crfsuite
Requires-Dist: rich-click
Requires-Dist: taxopy >=0.12.0
Requires-Dist: tensorflow >=2.16
Requires-Dist: xgboost >=1.6
Project-URL: Home, https://portal.nersc.gov/genomad/
Project-URL: Source, https://github.com/apcamargo/genomad/
